{
	"info": {
		"_postman_id": "67c57cfa-bee9-44da-912d-bb567dab5544",
		"name": "discussion-api",
		"schema": "https://schema.getpostman.com/json/collection/v2.1.0/collection.json"
	},
	"item": [
		{
			"name": "Category",
			"item": [
				{
					"name": "GET /categories",
					"request": {
						"method": "GET",
						"header": [],
						"url": {
							"raw": "{{BASE_URL}}/categories",
							"host": [
								"{{BASE_URL}}"
							],
							"path": [
								"categories"
							]
						}
					},
					"response": []
				},
				{
					"name": "POST /category",
					"request": {
						"method": "POST",
						"header": [],
						"body": {
							"mode": "raw",
							"raw": "{\n    \"category\": \"testing\"\n}",
							"options": {
								"raw": {
									"language": "json"
								}
							}
						},
						"url": {
							"raw": "{{BASE_URL}}/category",
							"host": [
								"{{BASE_URL}}"
							],
							"path": [
								"category"
							]
						}
					},
					"response": []
				},
				{
					"name": "UPDATE /category/:id",
					"request": {
						"method": "PUT",
						"header": [],
						"body": {
							"mode": "raw",
							"raw": "{\n    \"category\": \"testing-update\"\n}",
							"options": {
								"raw": {
									"language": "json"
								}
							}
						},
						"url": {
							"raw": "{{BASE_URL}}/category/5",
							"host": [
								"{{BASE_URL}}"
							],
							"path": [
								"category",
								"5"
							]
						}
					},
					"response": []
				},
				{
					"name": "GET /category",
					"request": {
						"method": "GET",
						"header": [],
						"url": {
							"raw": "{{BASE_URL}}/category/6",
							"host": [
								"{{BASE_URL}}"
							],
							"path": [
								"category",
								"6"
							]
						}
					},
					"response": []
				},
				{
					"name": "DELETE /category/:id",
					"request": {
						"method": "DELETE",
						"header": [],
						"url": {
							"raw": "{{BASE_URL}}/category/5",
							"host": [
								"{{BASE_URL}}"
							],
							"path": [
								"category",
								"5"
							]
						}
					},
					"response": []
				}
			],
			"protocolProfileBehavior": {}
		},
		{
			"name": "User",
			"item": [
				{
					"name": "GET /users",
					"request": {
						"method": "GET",
						"header": [],
						"url": {
							"raw": "{{BASE_URL}}/users",
							"host": [
								"{{BASE_URL}}"
							],
							"path": [
								"users"
							]
						}
					},
					"response": []
				},
				{
					"name": "POST /user",
					"request": {
						"method": "POST",
						"header": [],
						"body": {
							"mode": "raw",
							"raw": "{\n    \"first_name\": \"udin\",\n    \"last_name\": \"ganteng\",\n    \"avatar\": \"random\"\n}",
							"options": {
								"raw": {
									"language": "json"
								}
							}
						},
						"url": {
							"raw": "{{BASE_URL}}/user",
							"host": [
								"{{BASE_URL}}"
							],
							"path": [
								"user"
							]
						}
					},
					"response": []
				}
			],
			"protocolProfileBehavior": {}
		},
		{
			"name": "Comment",
			"item": [
				{
					"name": "POST /comment",
					"request": {
						"method": "POST",
						"header": [],
						"body": {
							"mode": "raw",
							"raw": "{\n    \"content\": \"this is udin comment\",\n    \"discussion_id\": 3,\n    \"user_id\":9   \n}",
							"options": {
								"raw": {
									"language": "json"
								}
							}
						},
						"url": {
							"raw": "{{BASE_URL}}/comment",
							"host": [
								"{{BASE_URL}}"
							],
							"path": [
								"comment"
							]
						}
					},
					"response": []
				},
				{
					"name": "GET /comments",
					"request": {
						"method": "GET",
						"header": [],
						"url": {
							"raw": "{{BASE_URL}}/comments",
							"host": [
								"{{BASE_URL}}"
							],
							"path": [
								"comments"
							]
						}
					},
					"response": []
				},
				{
					"name": "GET /comment/:id",
					"protocolProfileBehavior": {
						"disableBodyPruning": true
					},
					"request": {
						"method": "GET",
						"header": [],
						"body": {
							"mode": "raw",
							"raw": "",
							"options": {
								"raw": {
									"language": "json"
								}
							}
						},
						"url": {
							"raw": "{{BASE_URL}}/comment/11",
							"host": [
								"{{BASE_URL}}"
							],
							"path": [
								"comment",
								"11"
							]
						}
					},
					"response": []
				},
				{
					"name": "PUT /comment/:id",
					"request": {
						"method": "PUT",
						"header": [],
						"body": {
							"mode": "raw",
							"raw": "{\n    \"parent_id\": 0,\n    \"user_id\": 9,\n    \"discussion_id\": 3,\n    \"content\": \"udin comment\"\n}",
							"options": {
								"raw": {
									"language": "json"
								}
							}
						},
						"url": {
							"raw": "{{BASE_URL}}/comment/11",
							"host": [
								"{{BASE_URL}}"
							],
							"path": [
								"comment",
								"11"
							]
						}
					},
					"response": []
				},
				{
					"name": "DELETE /comment/:id",
					"request": {
						"method": "DELETE",
						"header": [],
						"url": {
							"raw": "{{BASE_URL}}/comment/10",
							"host": [
								"{{BASE_URL}}"
							],
							"path": [
								"comment",
								"10"
							]
						}
					},
					"response": []
				}
			],
			"protocolProfileBehavior": {}
		},
		{
			"name": "Discussion",
			"item": [
				{
					"name": "GET /discussions",
					"protocolProfileBehavior": {
						"disableBodyPruning": true
					},
					"request": {
						"method": "GET",
						"header": [],
						"body": {
							"mode": "raw",
							"raw": ""
						},
						"url": {
							"raw": "{{BASE_URL}}/discussions",
							"host": [
								"{{BASE_URL}}"
							],
							"path": [
								"discussions"
							]
						}
					},
					"response": []
				},
				{
					"name": "POST /discussions",
					"request": {
						"method": "POST",
						"header": [],
						"body": {
							"mode": "raw",
							"raw": "{\n    \"user_id\" : 1,\n    \"category_id\": 4,\n    \"title\": \"test-update discussion title\",\n    \"content\": \"test-update discussion content\"\n}",
							"options": {
								"raw": {
									"language": "json"
								}
							}
						},
						"url": {
							"raw": "{{BASE_URL}}/discussion",
							"host": [
								"{{BASE_URL}}"
							],
							"path": [
								"discussion"
							]
						}
					},
					"response": []
				},
				{
					"name": "GET /discussion/:id",
					"request": {
						"method": "GET",
						"header": [],
						"url": {
							"raw": "{{BASE_URL}}/discussion/6",
							"host": [
								"{{BASE_URL}}"
							],
							"path": [
								"discussion",
								"6"
							]
						}
					},
					"response": []
				},
				{
					"name": "PUT /discussion/:id",
					"request": {
						"method": "PUT",
						"header": [],
						"body": {
							"mode": "raw",
							"raw": "{\n    \"title\": \"random gan\",\n    \"content\": \"this is random gancontent\",\n    \"category_id\": 1,\n    \"user_id\": 1\n}",
							"options": {
								"raw": {
									"language": "json"
								}
							}
						},
						"url": {
							"raw": "{{BASE_URL}}/discussion/3",
							"host": [
								"{{BASE_URL}}"
							],
							"path": [
								"discussion",
								"3"
							]
						}
					},
					"response": []
				},
				{
					"name": "DELETE /discussion/:id",
					"request": {
						"method": "DELETE",
						"header": [],
						"url": {
							"raw": "{{BASE_URL}}/discussion/6",
							"host": [
								"{{BASE_URL}}"
							],
							"path": [
								"discussion",
								"6"
							]
						}
					},
					"response": []
				}
			],
			"protocolProfileBehavior": {}
		},
		{
			"name": "Uploader",
			"item": [
				{
					"name": "POST /upload",
					"request": {
						"method": "POST",
						"header": [],
						"body": {
							"mode": "formdata",
							"formdata": [
								{
									"key": "file",
									"type": "file",
									"src": "/home/zarszz/Pictures/pixel_google.jpg"
								},
								{
									"key": "discussion_id",
									"value": "3",
									"type": "text",
									"disabled": true
								}
							]
						},
						"url": {
							"raw": "{{BASE_URL}}/upload",
							"host": [
								"{{BASE_URL}}"
							],
							"path": [
								"upload"
							]
						}
					},
					"response": []
				},
				{
					"name": "POST /uploads",
					"request": {
						"method": "POST",
						"header": [],
						"body": {
							"mode": "formdata",
							"formdata": [
								{
									"key": "files",
									"type": "file",
									"src": [
										"/home/zarszz/Pictures/client-error.png",
										"/home/zarszz/Pictures/server-error.png",
										"/home/zarszz/Pictures/g00mana.png",
										"/home/zarszz/Pictures/server-mah-biasa.png"
									]
								}
							]
						},
						"url": {
							"raw": "{{BASE_URL}}/uploads",
							"host": [
								"{{BASE_URL}}"
							],
							"path": [
								"uploads"
							]
						}
					},
					"response": []
				}
			],
			"protocolProfileBehavior": {}
		}
	],
	"protocolProfileBehavior": {}
}